time_adapters/__init__.py
time_adapters/auto.py
time_adapters/graphene.py
time_adapters/postgres.py
time_adapters/sqlalchemy.py
time_adapters/sqlite.py
time_adapters-0.0.2.dist-info/LICENSE.txt
time_adapters-0.0.2.dist-info/METADATA
time_adapters-0.0.2.dist-info/WHEEL
time_adapters-0.0.2.dist-info/top_level.txt
time_adapters-0.0.2.dist-info/RECORD
