Metadata-Version: 2.1
Name: time_adapters
Version: 0.0.2
Summary: time adapters
Home-page: https://github.com/dpep/py_time_adapters
Author: Daniel Pepper
License: MIT
Platform: any
Classifier: License :: OSI Approved :: MIT License
Classifier: Natural Language :: English
Classifier: Operating System :: OS Independent
Classifier: Topic :: Utilities
